{
  "description": "",
  "enabled": true,
  "name": "Relative Humidity Per Younger Max",
  "organization_id": "58db17c424dc720001671378",
  "source_type": "sensor",
  "state": "ready",
  "station_id": "58e68caddf5ce600012602e0",
  "datapoints_config": [
    {
      "begins_at": "2015-09-02T23:50:00.000Z",
      "params": {
        "query": {
          "compact": true,
          "datastream_id": 4143,
          "time_adjust": -28800
        }
      },
      "path": "/legacy/datavalues-ucnrs"
    }
  ],
  "external_refs": [
    {
      "identifier": "4143",
      "type": "odm.datastreams.DatastreamID"
    },
    {
      "identifier": "363",
      "type": "odm.stations.StationID"
    },
    {
      "identifier": "Max_Relative_Humidity",
      "type": "odm.datastreams.FieldName"
    },
    {
      "identifier": "79",
      "type": "odm.stations.MethodID"
    },
    {
      "identifier": "ucyl_youngerlagoon",
      "type": "loggernet.station"
    },
    {
      "identifier": "wanda.berkeley.edu:1024",
      "type": "loggernet.ldmp"
    },
    {
      "identifier": "TenMin",
      "type": "loggernet.table"
    }
  ],
  "tags": [
    "ds_Medium_Air",
    "ds_Variable_RelativeHumidity",
    "dt_Unit_Percent",
    "ds_Aggregate_Maximum"
  ]
}