{
  "_id": "58e68cacdf5ce600012602c5",
  "enabled": true,
  "is_active": true,
  "is_stationary": true,
  "name": "McLaughlin",
  "organization_id": "58db17c424dc720001671378",
  "slug": "mclaughlin",
  "station_type": "weather",
  "time_zone": "PST",
  "utc_offset": -28800,
  "external_links": [
    {
      "title": "Metadata",
      "url": "http://sensor.berkeley.edu/cgi/sensor_show_tables?Access=4.00&username=Guest+User&MC_Name=UCNRS&table=stations&name=McLaughlin"
    },
    {
      "title": "Original Site",
      "url": "https://wrcc.dri.edu/weather/ucmc.html"
    }
  ],
  "external_refs": [
    {
      "identifier": "350",
      "type": "odm.station.StationID",
      "url": "file://ucmc_mclaughlin_dri.dat"
    },
    {
      "identifier": "ucmc_mclaughlin",
      "type": "loggernet.station"
    },
    {
      "identifier": "wanda.berkeley.edu:1024",
      "type": "loggernet.ldmp"
    },
    {
      "identifier": "TenMin",
      "type": "loggernet.data_tables"
    }
  ],
  "geo": {
    "coordinates": [
      -122.335,
      38.82416,
      402.336
    ],
    "type": "Point"
  },
  "media": [
    {
      "type": "photo",
      "sizes": {
        "thumb": {
          "h": 60,
          "w": 60,
          "url": "http://res.cloudinary.com/dendro/image/upload/c_fill,g_center,h_60,w_60/ucmc.S2.jpg"
        },
        "thumb2x": {
          "h": 120,
          "w": 120,
          "url": "http://res.cloudinary.com/dendro/image/upload/c_fill,g_center,h_120,w_120/ucmc.S2.jpg"
        },
        "small": {
          "h": 240,
          "w": 240,
          "url": "http://res.cloudinary.com/dendro/image/upload/c_fill,g_center,h_240,w_240/ucmc.S2.jpg"
        },
        "small2x": {
          "h": 480,
          "w": 480,
          "url": "http://res.cloudinary.com/dendro/image/upload/c_fill,g_center,h_480,w_480/ucmc.S2.jpg"
        },
        "medium": {
          "h": 480,
          "w": 240,
          "url": "http://res.cloudinary.com/dendro/image/upload/c_fill,g_center,h_480,w_480/ucmc.S2.jpg"
        },
        "medium2x": {
          "h": 960,
          "w": 960,
          "url": "http://res.cloudinary.com/dendro/image/upload/c_fill,g_center,h_960,w_960/ucmc.S2.jpg"
        },
        "large": {
          "h": 1080,
          "w": 1080,
          "url": "http://res.cloudinary.com/dendro/image/upload/c_fill,g_center,h_1080,w_1080/ucmc.S2.jpg"
        }
      }
    },
    {
      "type": "photo",
      "sizes": {
        "thumb": {
          "h": 60,
          "w": 60,
          "url": "http://res.cloudinary.com/dendro/image/upload/c_fill,g_center,h_60,w_60/ucmc.SE1.jpg"
        },
        "thumb2x": {
          "h": 120,
          "w": 120,
          "url": "http://res.cloudinary.com/dendro/image/upload/c_fill,g_center,h_120,w_120/ucmc.SE1.jpg"
        },
        "small": {
          "h": 240,
          "w": 240,
          "url": "http://res.cloudinary.com/dendro/image/upload/c_fill,g_center,h_240,w_240/ucmc.SE1.jpg"
        },
        "small2x": {
          "h": 480,
          "w": 480,
          "url": "http://res.cloudinary.com/dendro/image/upload/c_fill,g_center,h_480,w_480/ucmc.SE1.jpg"
        },
        "medium": {
          "h": 480,
          "w": 240,
          "url": "http://res.cloudinary.com/dendro/image/upload/c_fill,g_center,h_480,w_480/ucmc.SE1.jpg"
        },
        "medium2x": {
          "h": 960,
          "w": 960,
          "url": "http://res.cloudinary.com/dendro/image/upload/c_fill,g_center,h_960,w_960/ucmc.SE1.jpg"
        },
        "large": {
          "h": 1080,
          "w": 1080,
          "url": "http://res.cloudinary.com/dendro/image/upload/c_fill,g_center,h_1080,w_1080/ucmc.SE1.jpg"
        }
      }
    },
    {
      "type": "photo",
      "sizes": {
        "thumb": {
          "h": 60,
          "w": 60,
          "url": "http://res.cloudinary.com/dendro/image/upload/c_fill,g_center,h_60,w_60/ucmc.SE2.jpg"
        },
        "thumb2x": {
          "h": 120,
          "w": 120,
          "url": "http://res.cloudinary.com/dendro/image/upload/c_fill,g_center,h_120,w_120/ucmc.SE2.jpg"
        },
        "small": {
          "h": 240,
          "w": 240,
          "url": "http://res.cloudinary.com/dendro/image/upload/c_fill,g_center,h_240,w_240/ucmc.SE2.jpg"
        },
        "small2x": {
          "h": 480,
          "w": 480,
          "url": "http://res.cloudinary.com/dendro/image/upload/c_fill,g_center,h_480,w_480/ucmc.SE2.jpg"
        },
        "medium": {
          "h": 480,
          "w": 240,
          "url": "http://res.cloudinary.com/dendro/image/upload/c_fill,g_center,h_480,w_480/ucmc.SE2.jpg"
        },
        "medium2x": {
          "h": 960,
          "w": 960,
          "url": "http://res.cloudinary.com/dendro/image/upload/c_fill,g_center,h_960,w_960/ucmc.SE2.jpg"
        },
        "large": {
          "h": 1080,
          "w": 1080,
          "url": "http://res.cloudinary.com/dendro/image/upload/c_fill,g_center,h_1080,w_1080/ucmc.SE2.jpg"
        }
      }
    },
    {
      "type": "photo",
      "sizes": {
        "thumb": {
          "h": 60,
          "w": 60,
          "url": "http://res.cloudinary.com/dendro/image/upload/c_fill,g_center,h_60,w_60/ucmc.SW1.jpg"
        },
        "thumb2x": {
          "h": 120,
          "w": 120,
          "url": "http://res.cloudinary.com/dendro/image/upload/c_fill,g_center,h_120,w_120/ucmc.SW1.jpg"
        },
        "small": {
          "h": 240,
          "w": 240,
          "url": "http://res.cloudinary.com/dendro/image/upload/c_fill,g_center,h_240,w_240/ucmc.SW1.jpg"
        },
        "small2x": {
          "h": 480,
          "w": 480,
          "url": "http://res.cloudinary.com/dendro/image/upload/c_fill,g_center,h_480,w_480/ucmc.SW1.jpg"
        },
        "medium": {
          "h": 480,
          "w": 240,
          "url": "http://res.cloudinary.com/dendro/image/upload/c_fill,g_center,h_480,w_480/ucmc.SW1.jpg"
        },
        "medium2x": {
          "h": 960,
          "w": 960,
          "url": "http://res.cloudinary.com/dendro/image/upload/c_fill,g_center,h_960,w_960/ucmc.SW1.jpg"
        },
        "large": {
          "h": 1080,
          "w": 1080,
          "url": "http://res.cloudinary.com/dendro/image/upload/c_fill,g_center,h_1080,w_1080/ucmc.SW1.jpg"
        }
      }
    },
    {
      "type": "photo",
      "sizes": {
        "thumb": {
          "h": 60,
          "w": 60,
          "url": "http://res.cloudinary.com/dendro/image/upload/c_fill,g_center,h_60,w_60/ucmc.SW2.jpg"
        },
        "thumb2x": {
          "h": 120,
          "w": 120,
          "url": "http://res.cloudinary.com/dendro/image/upload/c_fill,g_center,h_120,w_120/ucmc.SW2.jpg"
        },
        "small": {
          "h": 240,
          "w": 240,
          "url": "http://res.cloudinary.com/dendro/image/upload/c_fill,g_center,h_240,w_240/ucmc.SW2.jpg"
        },
        "small2x": {
          "h": 480,
          "w": 480,
          "url": "http://res.cloudinary.com/dendro/image/upload/c_fill,g_center,h_480,w_480/ucmc.SW2.jpg"
        },
        "medium": {
          "h": 480,
          "w": 240,
          "url": "http://res.cloudinary.com/dendro/image/upload/c_fill,g_center,h_480,w_480/ucmc.SW2.jpg"
        },
        "medium2x": {
          "h": 960,
          "w": 960,
          "url": "http://res.cloudinary.com/dendro/image/upload/c_fill,g_center,h_960,w_960/ucmc.SW2.jpg"
        },
        "large": {
          "h": 1080,
          "w": 1080,
          "url": "http://res.cloudinary.com/dendro/image/upload/c_fill,g_center,h_1080,w_1080/ucmc.SW2.jpg"
        }
      }
    },
    {
      "type": "photo",
      "sizes": {
        "thumb": {
          "h": 60,
          "w": 60,
          "url": "http://res.cloudinary.com/dendro/image/upload/c_fill,g_center,h_60,w_60/ucmc.W1.jpg"
        },
        "thumb2x": {
          "h": 120,
          "w": 120,
          "url": "http://res.cloudinary.com/dendro/image/upload/c_fill,g_center,h_120,w_120/ucmc.W1.jpg"
        },
        "small": {
          "h": 240,
          "w": 240,
          "url": "http://res.cloudinary.com/dendro/image/upload/c_fill,g_center,h_240,w_240/ucmc.W1.jpg"
        },
        "small2x": {
          "h": 480,
          "w": 480,
          "url": "http://res.cloudinary.com/dendro/image/upload/c_fill,g_center,h_480,w_480/ucmc.W1.jpg"
        },
        "medium": {
          "h": 480,
          "w": 240,
          "url": "http://res.cloudinary.com/dendro/image/upload/c_fill,g_center,h_480,w_480/ucmc.W1.jpg"
        },
        "medium2x": {
          "h": 960,
          "w": 960,
          "url": "http://res.cloudinary.com/dendro/image/upload/c_fill,g_center,h_960,w_960/ucmc.W1.jpg"
        },
        "large": {
          "h": 1080,
          "w": 1080,
          "url": "http://res.cloudinary.com/dendro/image/upload/c_fill,g_center,h_1080,w_1080/ucmc.W1.jpg"
        }
      }
    },
    {
      "type": "photo",
      "sizes": {
        "thumb": {
          "h": 60,
          "w": 60,
          "url": "http://res.cloudinary.com/dendro/image/upload/c_fill,g_center,h_60,w_60/ucmc.W2.jpg"
        },
        "thumb2x": {
          "h": 120,
          "w": 120,
          "url": "http://res.cloudinary.com/dendro/image/upload/c_fill,g_center,h_120,w_120/ucmc.W2.jpg"
        },
        "small": {
          "h": 240,
          "w": 240,
          "url": "http://res.cloudinary.com/dendro/image/upload/c_fill,g_center,h_240,w_240/ucmc.W2.jpg"
        },
        "small2x": {
          "h": 480,
          "w": 480,
          "url": "http://res.cloudinary.com/dendro/image/upload/c_fill,g_center,h_480,w_480/ucmc.W2.jpg"
        },
        "medium": {
          "h": 480,
          "w": 240,
          "url": "http://res.cloudinary.com/dendro/image/upload/c_fill,g_center,h_480,w_480/ucmc.W2.jpg"
        },
        "medium2x": {
          "h": 960,
          "w": 960,
          "url": "http://res.cloudinary.com/dendro/image/upload/c_fill,g_center,h_960,w_960/ucmc.W2.jpg"
        },
        "large": {
          "h": 1080,
          "w": 1080,
          "url": "http://res.cloudinary.com/dendro/image/upload/c_fill,g_center,h_1080,w_1080/ucmc.W2.jpg"
        }
      }
    },
    {
      "type": "photo",
      "sizes": {
        "thumb": {
          "h": 60,
          "w": 60,
          "url": "http://res.cloudinary.com/dendro/image/upload/c_fill,g_center,h_60,w_60/ucmc.E1.jpg"
        },
        "thumb2x": {
          "h": 120,
          "w": 120,
          "url": "http://res.cloudinary.com/dendro/image/upload/c_fill,g_center,h_120,w_120/ucmc.E1.jpg"
        },
        "small": {
          "h": 240,
          "w": 240,
          "url": "http://res.cloudinary.com/dendro/image/upload/c_fill,g_center,h_240,w_240/ucmc.E1.jpg"
        },
        "small2x": {
          "h": 480,
          "w": 480,
          "url": "http://res.cloudinary.com/dendro/image/upload/c_fill,g_center,h_480,w_480/ucmc.E1.jpg"
        },
        "medium": {
          "h": 480,
          "w": 240,
          "url": "http://res.cloudinary.com/dendro/image/upload/c_fill,g_center,h_480,w_480/ucmc.E1.jpg"
        },
        "medium2x": {
          "h": 960,
          "w": 960,
          "url": "http://res.cloudinary.com/dendro/image/upload/c_fill,g_center,h_960,w_960/ucmc.E1.jpg"
        },
        "large": {
          "h": 1080,
          "w": 1080,
          "url": "http://res.cloudinary.com/dendro/image/upload/c_fill,g_center,h_1080,w_1080/ucmc.E1.jpg"
        }
      }
    },
    {
      "type": "photo",
      "sizes": {
        "thumb": {
          "h": 60,
          "w": 60,
          "url": "http://res.cloudinary.com/dendro/image/upload/c_fill,g_center,h_60,w_60/ucmc.E2.jpg"
        },
        "thumb2x": {
          "h": 120,
          "w": 120,
          "url": "http://res.cloudinary.com/dendro/image/upload/c_fill,g_center,h_120,w_120/ucmc.E2.jpg"
        },
        "small": {
          "h": 240,
          "w": 240,
          "url": "http://res.cloudinary.com/dendro/image/upload/c_fill,g_center,h_240,w_240/ucmc.E2.jpg"
        },
        "small2x": {
          "h": 480,
          "w": 480,
          "url": "http://res.cloudinary.com/dendro/image/upload/c_fill,g_center,h_480,w_480/ucmc.E2.jpg"
        },
        "medium": {
          "h": 480,
          "w": 240,
          "url": "http://res.cloudinary.com/dendro/image/upload/c_fill,g_center,h_480,w_480/ucmc.E2.jpg"
        },
        "medium2x": {
          "h": 960,
          "w": 960,
          "url": "http://res.cloudinary.com/dendro/image/upload/c_fill,g_center,h_960,w_960/ucmc.E2.jpg"
        },
        "large": {
          "h": 1080,
          "w": 1080,
          "url": "http://res.cloudinary.com/dendro/image/upload/c_fill,g_center,h_1080,w_1080/ucmc.E2.jpg"
        }
      }
    },
    {
      "type": "photo",
      "sizes": {
        "thumb": {
          "h": 60,
          "w": 60,
          "url": "http://res.cloudinary.com/dendro/image/upload/c_fill,g_center,h_60,w_60/ucmc.N1.jpg"
        },
        "thumb2x": {
          "h": 120,
          "w": 120,
          "url": "http://res.cloudinary.com/dendro/image/upload/c_fill,g_center,h_120,w_120/ucmc.N1.jpg"
        },
        "small": {
          "h": 240,
          "w": 240,
          "url": "http://res.cloudinary.com/dendro/image/upload/c_fill,g_center,h_240,w_240/ucmc.N1.jpg"
        },
        "small2x": {
          "h": 480,
          "w": 480,
          "url": "http://res.cloudinary.com/dendro/image/upload/c_fill,g_center,h_480,w_480/ucmc.N1.jpg"
        },
        "medium": {
          "h": 480,
          "w": 240,
          "url": "http://res.cloudinary.com/dendro/image/upload/c_fill,g_center,h_480,w_480/ucmc.N1.jpg"
        },
        "medium2x": {
          "h": 960,
          "w": 960,
          "url": "http://res.cloudinary.com/dendro/image/upload/c_fill,g_center,h_960,w_960/ucmc.N1.jpg"
        },
        "large": {
          "h": 1080,
          "w": 1080,
          "url": "http://res.cloudinary.com/dendro/image/upload/c_fill,g_center,h_1080,w_1080/ucmc.N1.jpg"
        }
      }
    },
    {
      "type": "photo",
      "sizes": {
        "thumb": {
          "h": 60,
          "w": 60,
          "url": "http://res.cloudinary.com/dendro/image/upload/c_fill,g_center,h_60,w_60/ucmc.N2.jpg"
        },
        "thumb2x": {
          "h": 120,
          "w": 120,
          "url": "http://res.cloudinary.com/dendro/image/upload/c_fill,g_center,h_120,w_120/ucmc.N2.jpg"
        },
        "small": {
          "h": 240,
          "w": 240,
          "url": "http://res.cloudinary.com/dendro/image/upload/c_fill,g_center,h_240,w_240/ucmc.N2.jpg"
        },
        "small2x": {
          "h": 480,
          "w": 480,
          "url": "http://res.cloudinary.com/dendro/image/upload/c_fill,g_center,h_480,w_480/ucmc.N2.jpg"
        },
        "medium": {
          "h": 480,
          "w": 240,
          "url": "http://res.cloudinary.com/dendro/image/upload/c_fill,g_center,h_480,w_480/ucmc.N2.jpg"
        },
        "medium2x": {
          "h": 960,
          "w": 960,
          "url": "http://res.cloudinary.com/dendro/image/upload/c_fill,g_center,h_960,w_960/ucmc.N2.jpg"
        },
        "large": {
          "h": 1080,
          "w": 1080,
          "url": "http://res.cloudinary.com/dendro/image/upload/c_fill,g_center,h_1080,w_1080/ucmc.N2.jpg"
        }
      }
    },
    {
      "type": "photo",
      "sizes": {
        "thumb": {
          "h": 60,
          "w": 60,
          "url": "http://res.cloudinary.com/dendro/image/upload/c_fill,g_center,h_60,w_60/ucmc.NE1.jpg"
        },
        "thumb2x": {
          "h": 120,
          "w": 120,
          "url": "http://res.cloudinary.com/dendro/image/upload/c_fill,g_center,h_120,w_120/ucmc.NE1.jpg"
        },
        "small": {
          "h": 240,
          "w": 240,
          "url": "http://res.cloudinary.com/dendro/image/upload/c_fill,g_center,h_240,w_240/ucmc.NE1.jpg"
        },
        "small2x": {
          "h": 480,
          "w": 480,
          "url": "http://res.cloudinary.com/dendro/image/upload/c_fill,g_center,h_480,w_480/ucmc.NE1.jpg"
        },
        "medium": {
          "h": 480,
          "w": 240,
          "url": "http://res.cloudinary.com/dendro/image/upload/c_fill,g_center,h_480,w_480/ucmc.NE1.jpg"
        },
        "medium2x": {
          "h": 960,
          "w": 960,
          "url": "http://res.cloudinary.com/dendro/image/upload/c_fill,g_center,h_960,w_960/ucmc.NE1.jpg"
        },
        "large": {
          "h": 1080,
          "w": 1080,
          "url": "http://res.cloudinary.com/dendro/image/upload/c_fill,g_center,h_1080,w_1080/ucmc.NE1.jpg"
        }
      }
    },
    {
      "type": "photo",
      "sizes": {
        "thumb": {
          "h": 60,
          "w": 60,
          "url": "http://res.cloudinary.com/dendro/image/upload/c_fill,g_center,h_60,w_60/ucmc.NE2.jpg"
        },
        "thumb2x": {
          "h": 120,
          "w": 120,
          "url": "http://res.cloudinary.com/dendro/image/upload/c_fill,g_center,h_120,w_120/ucmc.NE2.jpg"
        },
        "small": {
          "h": 240,
          "w": 240,
          "url": "http://res.cloudinary.com/dendro/image/upload/c_fill,g_center,h_240,w_240/ucmc.NE2.jpg"
        },
        "small2x": {
          "h": 480,
          "w": 480,
          "url": "http://res.cloudinary.com/dendro/image/upload/c_fill,g_center,h_480,w_480/ucmc.NE2.jpg"
        },
        "medium": {
          "h": 480,
          "w": 240,
          "url": "http://res.cloudinary.com/dendro/image/upload/c_fill,g_center,h_480,w_480/ucmc.NE2.jpg"
        },
        "medium2x": {
          "h": 960,
          "w": 960,
          "url": "http://res.cloudinary.com/dendro/image/upload/c_fill,g_center,h_960,w_960/ucmc.NE2.jpg"
        },
        "large": {
          "h": 1080,
          "w": 1080,
          "url": "http://res.cloudinary.com/dendro/image/upload/c_fill,g_center,h_1080,w_1080/ucmc.NE2.jpg"
        }
      }
    },
    {
      "type": "photo",
      "sizes": {
        "thumb": {
          "h": 60,
          "w": 60,
          "url": "http://res.cloudinary.com/dendro/image/upload/c_fill,g_center,h_60,w_60/ucmc.NW1.jpg"
        },
        "thumb2x": {
          "h": 120,
          "w": 120,
          "url": "http://res.cloudinary.com/dendro/image/upload/c_fill,g_center,h_120,w_120/ucmc.NW1.jpg"
        },
        "small": {
          "h": 240,
          "w": 240,
          "url": "http://res.cloudinary.com/dendro/image/upload/c_fill,g_center,h_240,w_240/ucmc.NW1.jpg"
        },
        "small2x": {
          "h": 480,
          "w": 480,
          "url": "http://res.cloudinary.com/dendro/image/upload/c_fill,g_center,h_480,w_480/ucmc.NW1.jpg"
        },
        "medium": {
          "h": 480,
          "w": 240,
          "url": "http://res.cloudinary.com/dendro/image/upload/c_fill,g_center,h_480,w_480/ucmc.NW1.jpg"
        },
        "medium2x": {
          "h": 960,
          "w": 960,
          "url": "http://res.cloudinary.com/dendro/image/upload/c_fill,g_center,h_960,w_960/ucmc.NW1.jpg"
        },
        "large": {
          "h": 1080,
          "w": 1080,
          "url": "http://res.cloudinary.com/dendro/image/upload/c_fill,g_center,h_1080,w_1080/ucmc.NW1.jpg"
        }
      }
    },
    {
      "type": "photo",
      "sizes": {
        "thumb": {
          "h": 60,
          "w": 60,
          "url": "http://res.cloudinary.com/dendro/image/upload/c_fill,g_center,h_60,w_60/ucmc.NW2.jpg"
        },
        "thumb2x": {
          "h": 120,
          "w": 120,
          "url": "http://res.cloudinary.com/dendro/image/upload/c_fill,g_center,h_120,w_120/ucmc.NW2.jpg"
        },
        "small": {
          "h": 240,
          "w": 240,
          "url": "http://res.cloudinary.com/dendro/image/upload/c_fill,g_center,h_240,w_240/ucmc.NW2.jpg"
        },
        "small2x": {
          "h": 480,
          "w": 480,
          "url": "http://res.cloudinary.com/dendro/image/upload/c_fill,g_center,h_480,w_480/ucmc.NW2.jpg"
        },
        "medium": {
          "h": 480,
          "w": 240,
          "url": "http://res.cloudinary.com/dendro/image/upload/c_fill,g_center,h_480,w_480/ucmc.NW2.jpg"
        },
        "medium2x": {
          "h": 960,
          "w": 960,
          "url": "http://res.cloudinary.com/dendro/image/upload/c_fill,g_center,h_960,w_960/ucmc.NW2.jpg"
        },
        "large": {
          "h": 1080,
          "w": 1080,
          "url": "http://res.cloudinary.com/dendro/image/upload/c_fill,g_center,h_1080,w_1080/ucmc.NW2.jpg"
        }
      }
    },
    {
      "type": "photo",
      "sizes": {
        "thumb": {
          "h": 60,
          "w": 60,
          "url": "http://res.cloudinary.com/dendro/image/upload/c_fill,g_center,h_60,w_60/ucmc.S1.jpg"
        },
        "thumb2x": {
          "h": 120,
          "w": 120,
          "url": "http://res.cloudinary.com/dendro/image/upload/c_fill,g_center,h_120,w_120/ucmc.S1.jpg"
        },
        "small": {
          "h": 240,
          "w": 240,
          "url": "http://res.cloudinary.com/dendro/image/upload/c_fill,g_center,h_240,w_240/ucmc.S1.jpg"
        },
        "small2x": {
          "h": 480,
          "w": 480,
          "url": "http://res.cloudinary.com/dendro/image/upload/c_fill,g_center,h_480,w_480/ucmc.S1.jpg"
        },
        "medium": {
          "h": 480,
          "w": 240,
          "url": "http://res.cloudinary.com/dendro/image/upload/c_fill,g_center,h_480,w_480/ucmc.S1.jpg"
        },
        "medium2x": {
          "h": 960,
          "w": 960,
          "url": "http://res.cloudinary.com/dendro/image/upload/c_fill,g_center,h_960,w_960/ucmc.S1.jpg"
        },
        "large": {
          "h": 1080,
          "w": 1080,
          "url": "http://res.cloudinary.com/dendro/image/upload/c_fill,g_center,h_1080,w_1080/ucmc.S1.jpg"
        }
      }
    }
  ],
  "created_at": "2018-07-02T01:05:53.206Z",
  "updated_at": "2018-07-03T19:03:53.524Z"
}