{
  "_id": "5ae87a67fe27f4a45210309a",
  "description": "",
  "name": "Total Solar Radiation W m2 Avg",
  "organization_id": "58db17c424dc720001671378",
  "source_type": "sensor",
  "state": "ready",
  "station_id": "58e68cacdf5ce600012602c5",
  "datapoints_config": [
    {
      "begins_at": "2011-12-14T22:20:00.000Z",
      "params": {
        "query": {
          "compact": true,
          "datastream_id": 3696,
          "time_adjust": -28800
        }
      },
      "path": "/legacy/datavalues-ucnrs",
      "ends_before": "2017-02-01T11:10:00.000Z"
    },
    {
      "params": {
        "query": {
          "api": "ucnrs",
          "db": "station_ucmc_mclaughlin",
          "fc": "source_tenmin",
          "sc": "\"time\", \"RS_kw_m2_Avg\"*1000 as \"RS_w_m2_Avg\"",
          "utc_offset": -28800,
          "coalesce": false
        }
      },
      "begins_at": "2017-02-01T11:10:00.000Z",
      "path": "/influx/select"
    }
  ],
  "external_refs": [
    {
      "identifier": "3696",
      "type": "odm.datastreams.DatastreamID"
    },
    {
      "identifier": "350",
      "type": "odm.stations.StationID"
    },
    {
      "identifier": "Solar_Radiation",
      "type": "odm.datastreams.FieldName"
    },
    {
      "identifier": "81",
      "type": "odm.stations.MethodID"
    },
    {
      "identifier": "Solar Radiation Avg W/m^2",
      "type": "odm.stations.VariableCode"
    },
    {
      "identifier": "ucmc_mclaughlin",
      "type": "loggernet.station"
    },
    {
      "identifier": "Total Solar Radiation W m2 McLaughlin Avg",
      "type": "name_previous"
    }
  ],
  "is_enabled": true,
  "terms": {
    "ds": {
      "Medium": "Solar",
      "Variable": "Radiation",
      "Aggregate": "Average"
    },
    "dt": {
      "Unit": "WattPerSquareMeter"
    },
    "dq": {
      "Measurement": "SolarRadiation",
      "Purpose": "ReadytoUse"
    }
  },
  "is_geo_protected": false,
  "is_hidden": false,
  "version_id": "5d708ecb5a3a94f3f9902574",
  "updated_at": "2019-09-05T04:27:55.378Z",
  "updated_by": "5cdd9abda6fa68f95479675b",
  "created_at": "2019-05-16T18:43:06.422Z",
  "created_by": "5cdd9abda6fa68f95479675b",
  "terms_info": {
    "class_keys": [
      "dq__Measurement_SolarRadiation__Purpose_ReadytoUse",
      "ds__Aggregate_Average__Medium_Solar__Variable_Radiation"
    ],
    "class_tags": [
      "dq_Measurement_SolarRadiation",
      "dq_Purpose_ReadytoUse",
      "ds_Aggregate_Average",
      "ds_Medium_Solar",
      "ds_Variable_Radiation"
    ],
    "unit_tag": "dt_Unit_WattPerSquareMeter"
  }
}
