{
  "_id": "5ae873f3fe27f4d412102502",
  "enabled": false,
  "name": "BP Treebeard",
  "organization_id": "58db17e824dc720001671379",
  "source_type": "sensor",
  "state": "ready",
  "station_id": "58e68cacdf5ce600012602da",
  "datapoints_config": [
    {
      "begins_at": "2008-11-13T01:55:00.000Z",
      "ends_before": "2011-01-25T08:00:00.000Z",
      "params": {
        "query": {
          "compact": true,
          "datastream_id": 462,
          "time_adjust": -28800
        }
      },
      "path": "/legacy/datavalues2"
    }
  ],
  "external_refs": [
    {
      "identifier": "462",
      "type": "odm.datastreams.DatastreamID"
    },
    {
      "identifier": "48",
      "type": "odm.stations.StationID"
    },
    {
      "identifier": "airpressure_Avg",
      "type": "odm.datastreams.FieldName"
    },
    {
      "identifier": "36",
      "type": "odm.stations.MethodID"
    },
    {
      "identifier": "Barometric Pressure mb",
      "type": "odm.stations.VariableCode"
    },
    {
      "identifier": "WSTB_CR1000",
      "type": "loggernet.station"
    }
  ],
  "tags": [
    "ds_Medium_Air",
    "ds_Variable_BarometricPressure",
    "dt_Unit_Millibar",
    "ds_Aggregate_Average"
  ],
  "created_at": "2018-07-01T22:53:57.273Z",
  "updated_at": "2018-07-03T19:02:51.850Z",
  "tags_info": {
    "resolved_terms": [
      {
        "label": "Air",
        "scheme_id": "ds",
        "scheme_priority": 10,
        "vocabulary_id": "ds-medium",
        "vocabulary_label": "Medium"
      },
      {
        "label": "BarometricPressure",
        "scheme_id": "ds",
        "scheme_priority": 10,
        "vocabulary_id": "ds-variable",
        "vocabulary_label": "Variable"
      },
      {
        "abbreviation": "mb",
        "label": "Millibar",
        "scheme_id": "dt",
        "scheme_priority": 10,
        "vocabulary_id": "dt-unit",
        "vocabulary_label": "Unit"
      },
      {
        "label": "Average",
        "scheme_id": "ds",
        "scheme_priority": 10,
        "vocabulary_id": "ds-aggregate",
        "vocabulary_label": "Aggregate"
      }
    ],
    "scheme_refs": [
      {
        "_id": "ds",
        "tag_count": 3
      },
      {
        "_id": "dt",
        "tag_count": 1
      }
    ],
    "vocabulary_refs": [
      {
        "_id": "ds-medium"
      },
      {
        "_id": "ds-variable"
      },
      {
        "_id": "dt-unit"
      },
      {
        "_id": "ds-aggregate"
      }
    ]
  },
  "hashes": [
    {
      "key": "src",
      "str": "b7db56d4fa84bb62a0bc45ed765b5c97f0b4c811"
    },
    {
      "key": "att",
      "str": "da39a3ee5e6b4b0d3255bfef95601890afd80709"
    },
    {
      "key": "geo",
      "str": "da39a3ee5e6b4b0d3255bfef95601890afd80709"
    },
    {
      "key": "tag",
      "str": "d97826b01ce9e1934f5ed5c1c071d736b1cac5eb",
      "scheme_id": "ds"
    },
    {
      "key": "tag",
      "str": "f6e143fd7229fe4fb31a03055310db4b5f29e664",
      "scheme_id": "dt"
    }
  ],
  "_include": [],
  "description": "undefinedoriginal datastream name was BP Treebeard"
}